{
  "last_updated": "2025-11-10T10:40:20.374665Z",
  "source": "exchangerate-api",
  "base_currency": "USD",
  "rates": {
    "VND": {
      "name": "Vietnamese Dong",
      "rate": 26143.3712,
      "changes": {
        "1D": null,
        "1W": null,
        "1M": -0.4758475941288573
      }
    },
    "TRY": {
      "name": "Turkish Lira",
      "rate": 42.2433,
      "changes": {
        "1D": null,
        "1W": null,
        "1M": 1.1902822758369502
      }
    },
    "MNT": {
      "name": "Mongolian Tugrik",
      "rate": 3566.9801,
      "changes": {
        "1D": null,
        "1W": null,
        "1M": -0.13026535455339214
      }
    },
    "UZS": {
      "name": "Uzbek Som",
      "rate": 12173.1224,
      "changes": {
        "1D": null,
        "1W": null,
        "1M": 0.7986137642969379
      }
    },
    "AMD": {
      "name": "Armenian Dram",
      "rate": 382.7094,
      "changes": {
        "1D": null,
        "1W": null,
        "1M": -0.0006009745717183684
      }
    },
    "GBP": {
      "name": "British Pound Sterling",
      "rate": 0.7609,
      "changes": {
        "1D": null,
        "1W": null,
        "1M": 1.9699812382739275
      }
    }
  }
}